Workbook

Sheet Summary
A1: Case-study coverage in 06_Interview_Prep — summary
A3: Category | B3: Count
A4: Worked system design | B4: =COUNTIF('Case Studies'!$B:$B,A4)
A5: Worksheet + answer key | B5: =COUNTIF('Case Studies'!$B:$B,A5)
A6: Mock interview | B6: =COUNTIF('Case Studies'!$B:$B,A6)
A7: Cost/latency drill case | B7: =COUNTIF('Case Studies'!$B:$B,A7)
A8: Decomposition prompt | B8: =COUNTIF('Case Studies'!$B:$B,A8)
A9: Running module case | B9: =COUNTIF('Case Studies'!$B:$B,A9)
A10: Reported prompt | B10: =COUNTIF('Case Studies'!$B:$B,A10)
A11: Incident scenario | B11: =COUNTIF('Case Studies'!$B:$B,A11)
A12: Study-guide mock design | B12: =COUNTIF('Case Studies'!$B:$B,A12)
A13: Cost/latency production scenario | B13: =COUNTIF('Case Studies'!$B:$B,A13)
A14: Total named cases | B14: =SUM(B4:B13)
A15: Check: rows in Case Studies sheet | B15: =COUNTA('Case Studies'!$A:$A)-1
A16: Vendor PDF casebooks (not enumerated) | B16: =COUNTA('PDF Casebooks'!$A:$A)-1
A18: By collection
A19: Collection | B19: Count
A20: Handbook Module 09 — AI System Design Casebook | B20: =COUNTIF('Case Studies'!$D:$D,A20)
A21: Handbook Module 09 — 60-minute whiteboard scripts | B21: =COUNTIF('Case Studies'!$D:$D,A21)
A22: Cracking Agentic AI System Design Interviews — Ch 28 | B22: =COUNTIF('Case Studies'!$D:$D,A22)
A23: Handbook Module 07 — Multi-Agent Systems | B23: =COUNTIF('Case Studies'!$D:$D,A23)
A24: Handbook Module 02 — System Design Fundamentals | B24: =COUNTIF('Case Studies'!$D:$D,A24)
A25: FDE System Design Interview — 20 Scenarios (Version 3) | B25: =COUNTIF('Case Studies'!$D:$D,A25)
A26: Complete GEN AI FDE Interview System — Module 01 worksheets | B26: =COUNTIF('Case Studies'!$D:$D,A26)
A27: Complete GEN AI FDE Interview System — Module 07 mocks | B27: =COUNTIF('Case Studies'!$D:$D,A27)
A28: Study Guides — Cost & Latency Optimization (§16) | B28: =COUNTIF('Case Studies'!$D:$D,A28)
A29: OpenAI Applied — Problem Decomposition question bank | B29: =COUNTIF('Case Studies'!$D:$D,A29)
A30: Handbook Module 04 — Enterprise RAG | B30: =COUNTIF('Case Studies'!$D:$D,A30)
A31: Handbook Module 05 — Agentic Workflow Platforms | B31: =COUNTIF('Case Studies'!$D:$D,A31)
... A37: Study Guides — Cost & Latency Optimization (additions beyond the playbook, section E) | B37: =COUNTIF('Case Studies'!$D:$D,A37)
A38: Total | B38: =SUM(B20:B37)
A40: Notes: counts are live COUNTIF formulas over the Case Studies sheet. Duplicated copies (older System_Design and Delivery folder, Handbook/11 stories, site/content mirror) are recorded in 'Also appears in', not as separate rows. Git tracking: every .md is tracked; vendor PDF/docx under FDE/ are excluded by the path-anchored .gitignore rule. Built 2026-09-23.
A42: Grouping
A43: Groups of near-identical cases | B43: =COUNTA(Groups!$A:$A)-2
A44: Anchor cases to prepare (one per group) | B44: =COUNTIF('Case Studies'!$D:$D,"ANCHOR — prepare this")
A45: Cases covered by an anchor (read delta only) | B45: =COUNTIF('Case Studies'!$D:$D,"Covered by anchor — read delta only")
A46: Cost/latency questions on a grouped system (7 drills + 18 production scenarios + 2 latency prompts) | B46: =COUNTIF('Case Studies'!$D:$D,"Same system, cost/latency question — 10-min add-on")
A47: Standalone cases to prepare on their own | B47: =COUNTIF('Case Studies'!$D:$D,"Prepare on its own")
A48: Distinct preparations needed (anchors + standalone) | B48: =B44+B47
A49: Check: roles sum to all cases | B49: =B44+B45+B46+B47
A50: Playbook cost/latency drills attached to an anchor (Drill Add-ons tab) | B50: =COUNTIF('Drill Add-ons'!$I:$I,"Playbook")
A51: Self-drills written for anchors with no playbook case (Drill Add-ons tab) | B51: =COUNTIF('Drill Add-ons'!$I:$I,"Self-drill")
A52: Anchors with a cost/latency angle prepared (should equal 16) | B52: =B50+B51
A53: Cases with a prep pack linked (Case Studies, Prep pack column) | B53: =COUNTA('Case Studies'!$N:$N)-1
A54: Standalone cases with a pack in Case_Study_Groups/Standalone/ | B54: =COUNTIF('Case Studies'!$N:$N,"Standalone/*")
A55: Cases with a live site page (Case Studies, Site page column) | B55: =COUNTIF('Case Studies'!$O:$O,"https://*")

Sheet Groups
A1: Group | B1: Prepare this (#) | C1: Anchor case | D1: Members (#) | E1: Why these are the same case | F1: Other members — what to read beyond the anchor | G1: Anchor selection rule | H1: Day-before pack (Case_Study_Groups/) | I1: Site page (Forward Deployed)
A2: G01 Enterprise knowledge assistant (permission-aware RAG) | B2: 15 | C2: Enterprise Knowledge Assistant with RAG (book ch 1) | D2: #15, #6, #7, #27, #45, #57, #63, #38, #72, #70, #86, #93, #94, #106, #111, #112, #117 | E2: Every member is 'employees ask questions over Drive/SharePoint/Slack/wiki/tickets' where the hard part is permission fidelity, freshness and citations. | F2: #6 Enterprise RAG with Access Control — 60-min whiteboard script of the same design. Use it to rehearse timing; content is the anchor's. #7 Enterprise RAG on Databricks — Databricks/Lakehouse variant. Delta: leads with the Vector Search trap and Unity Catalog ACLs. Worth 15 min given your employer. #27 Internal Knowledge Assistant for Enterprise Support — Purchased worksheet, templated answer key. Delta: support-agent persona and ticket-note drafting. Nothing new architecturally. #45 Enterprise Knowledge Assistant — Question-bank version of the same prompt. Talking points only. #57 AI Search Across Many Enterprise Data Sources — Same prompt phrased as 'unified search'. Delta: connector/indexing fan-out across 6 sources; say 'federated vs indexed' once. #63 Meridian Assist — enterprise RAG — Running case (Meridian Assist) the anchor is built on; also your STAR story. Read once for narrative, not design. #38 Enterprise legal RAG assistant under strict cost limits — Cost angle: legal RAG under a strict budget with citations and < 8 s. See Drill Add-ons tab. #72 Design an AI chatbot / an LLM-powered enterprise search system — Reported OpenAI prompt: 'LLM-powered enterprise search'. The anchor is the answer. #70 Sub-100 ms LLM-powered search when the naive RAG flow is 1.5 s: walk me to 100 ms — Latency angle: 1.5 s naive RAG to sub-100 ms. Decompose the budget: cache embeddings and retrieval, pre-filter, skip rerank on cache hits, small model, stream. Say what 100 ms rules out (any LLM generation on the hot path). #86 Stale index causes wrong prior-authorization policy answer — Incident: stale index gives a wrong policy answer. The anchor's missed-deletion failure path and reconciliation drill. #93 Prompt injection from a retrieved Confluence article — Incident: prompt injection from a retrieved Confluence page. Retrieved content is evidence, never instructions; tool gateway blocks the exfil. #94 Embedding-model change degrades recall through vector drift — Incident: embedding-model change causes vector drift. Re-chunking or re-embedding is a retrieval-model change: versioned index, offline eval, staged cutover. #106 RAG retrieval became slow after adding more documents — §15 scenario 3: retrieval slow as the corpus grows. Index partitioning, ACL pre-filter, top-k discipline. #111 Vector database query latency increased — §15 scenario 8: vector DB query latency. Filters, index type, warm caches, over-retrieval caps. #112 Reranker improved quality but doubled latency — §15 scenario 9: reranker doubled latency. Gate the rerank: only ambiguous queries, smaller candidate set, cheaper reranker. #117 Long context window caused poor performance — §15 scenario 14: long context hurt quality. Tight candidate set beats prompt stuffing; compress evidence. | G2: Prefer, in order: bespoke 20-Scenarios worksheet with answer key + V1/V2 tutorials > Handbook/Cracking worked design or whiteboard script > purchased worksheet (templated answer keys) > question-bank entry > cost/latency drill. | H2: G01_Enterprise_Knowledge_Assistant/ | I2: https://forward-deployed-sigma.vercel.app/modules/15-fde-case-studies/knowledge-retrieval/enterprise-knowledge-assistant
A3: G02 Customer-support automation | B3: 18 | C3: AI Customer-Support Automation (book ch 4) | D3: #18, #2, #46, #37, #35, #33, #39, #95, #96, #97, #99, #101, #102 | E3: Customer/ticket comes in, assistant retrieves KB + account context, drafts or acts within policy, escalates risky cases with full context. | F3: #2 Customer Support Assistant — Casebook worked design at 1M conversations/day. Delta: three memory layers, planner justification, model routing. Read the memory + routing sections. #46 Customer-Support Agent — Question-bank version. Talking points only. #37 Agentic Support Workflow — Mock-interview transcript of the same system. Use for a timed run, not new content. #35 ServiceNow Ticket Automation Agent — ITSM flavour (ServiceNow). Delta: classify/priority + assignment + KB. Same spine; mention ITIL change control. #33 Multi-Tenant SaaS Support Assistant — Support assistant with tenant isolation as the risk. Delta: tenant predicate on every retrieval — borrow from G07 anchor. #39 Support chatbot with 10,000 daily users — Cost angle: spend rising faster than deflection. Prepare the routing/caching answer, not the system. #95 Real-time multilingual support-ticket triage agent — Study-guide mock (LangChain): multilingual ticket triage. Delta: language detection and routing chain. #96 Real-time, human-gated support-ticket agent — Study-guide mock (LangGraph): human-gated ticket agent. Delta: interrupt/approval node mechanics. #97 Real-time agentic RAG support assistant — Study-guide mock (RAG): agentic RAG support assistant. Delta: retrieval grading and rewrite loop. #99 Real-time customer-support search over a fragmented, growing knowledge base — Study-guide mock (advanced RAG): support search over a fragmented, growing KB. Delta: parent-document and multi-index retrieval. #101 Real-time customer-support agent for a travel booking platform — Study-guide mock (agents): travel-booking support agent. Delta: tool design for bookings and cancellations. #102 Real-time customer-support agent over a growing knowledge base — Study-guide mock (parent-document retrieval): support agent over a growing KB. Delta: chunk-vs-parent retrieval trade-off. | H3: G02_Customer_Support_Automation/ | I3: https://forward-deployed-sigma.vercel.app/modules/15-fde-case-studies/agents-that-act/customer-support-automation
A4: G03 Tool-using agent acting across enterprise systems | B4: 22 | C4: Tool-Using AI Agent with Safety Controls (book ch 11) | D4: #22, #1, #50, #82, #90, #107, #118 | E4: An agent that reads requests and takes actions in CRM/ERP/email/ticketing. The interview probes authority, approval, reversibility and audit. | F4: #1 Enterprise AI Assistant over 100+ internal applications — Casebook design over 100+ internal apps. Delta: REST vs function-calling vs MCP as layers, tool registry at scale, identity propagation. Read that layering section. #50 AI Agent for Enterprise Workflow Automation — Question-bank version (Salesforce/SAP/Jira/email). Talking points only. #82 Architect an AI agent system: agent loop, tool interfaces, memory design, orchestration, safety — Reported Salesforce prompt: loop, tools, memory, orchestration, safety. The anchor plus #1's layering section covers it. #90 Agent tool-call near miss on refunds above the approval threshold — Incident: refund tool called above the approval threshold. The gateway blocked it; the fix is plan-level policy before tool selection. #107 Agent keeps calling tools repeatedly — §15 scenario 4: agent keeps calling tools. Step caps, in-request caching of tool results, deterministic routes. #118 Tool-calling workflow times out — §15 scenario 15: tool-calling workflow times out. Per-tool timeouts, parallel read-only calls, bounded execution graph. | H4: G03_Tool_Using_Agent_With_Safety_Controls/ | I4: https://forward-deployed-sigma.vercel.app/modules/15-fde-case-studies/agents-that-act/tool-using-agent-with-safety-controls
A5: G04 SRE / incident-response agent | B5: 11 | C5: Incident Response Agent for an SRE team | D5: #11, #32, #58 | E5: Alert fires, agent correlates logs/metrics/traces/deploys/runbooks, proposes cause, runs only safe diagnostics unless approved. | F5: #32 SRE Incident Triage Agent — Purchased worksheet + short/full mock. Delta: none architecturally; use the mock for a timed run. #58 AI-Powered Operations or Incident-Response Assistant — Question-bank version. Talking points only. | H5: G04_SRE_Incident_Response_Agent/ | I5: https://forward-deployed-sigma.vercel.app/modules/15-fde-case-studies/agents-that-act/sre-incident-response-agent
A6: G05 Sales copilot / account research | B6: 28 | C6: Sales Copilot for Account Executives | D6: #28, #48, #40 | E6: AE prepares for a meeting: account summary, opportunity risks, drafts, CRM update suggestions. | F6: #48 AI-Powered Sales or Account-Research Assistant — Question-bank version. Talking points only. #40 Reduce latency for an agentic CRM assistant — Latency angle: account prep takes 30–45 s. Prepare parallel tool calls + pre-computation answer. | H6: G05_Sales_Copilot/ | I6: https://forward-deployed-sigma.vercel.app/modules/15-fde-case-studies/agents-that-act/sales-copilot
A7: G06 Natural language over governed data (NL-to-SQL, KPI copilot) | B7: 17 | C7: Natural-Language-to-SQL Analytics Assistant (book ch 3) | D7: #17, #36, #34, #13 | E7: Business users ask metric questions; the system maps them to governed definitions and must not answer the wrong question with valid SQL. | F7: #36 Executive Dashboard Copilot — Executive persona of the same system. Delta: variance explanation + escalate to analysts. 5 minutes. #34 Retail Demand Forecast Explanation Assistant — Retail planner persona: explain forecast variance from sales/promo/weather data. Delta: driver attribution, human-reviewed actions. #13 From Supervisor to Deep Agent — Your AIA governed-data assistant told as architecture evolution (supervisor → deep agent). Delta: multi-agent evolution; also your STAR story. | H7: G06_NL_Over_Governed_Data/ | I7: https://forward-deployed-sigma.vercel.app/modules/15-fde-case-studies/knowledge-retrieval/nl-over-governed-data
A8: G07 Secure multi-tenant AI platform | B8: 16 | C8: Secure Multi-Tenant AI Platform (book ch 2) | D8: #16, #41, #85, #108 | E8: One application serving hundreds of tenants; the failure is a missing tenant predicate, plus per-tenant budgets and regional controls. | F8: #41 Multi-tenant GenAI platform with per-customer budgets — Cost angle: per-customer budgets and isolation. Prepare metering + quota answer. #85 Cross-tenant retrieval leak through a missing metadata filter — Incident: cross-tenant leak via a missing metadata filter. The anchor's tenant predicate is the fix; rehearse detect → contain → root-cause → prevent. #108 One tenant has unusually high usage — §15 scenario 5: one tenant has unusually high usage. Per-tenant attribution, quotas, noisy-neighbour limits. | H8: G07_Secure_Multi_Tenant_AI_Platform/ | I8: https://forward-deployed-sigma.vercel.app/modules/15-fde-case-studies/platforms-and-scale/secure-multi-tenant-ai-platform
A9: G08 Document review / extraction copilot with policy check | B9: 30 | C9: Healthcare Prior Authorization Assistant | D9: #30, #29, #31, #47, #56, #89, #92 | E9: Document comes in → structured extraction → compare against policy/playbook/criteria → flag gaps → route material cases to a human approver. | F9: #29 Financial Compliance Document Reviewer — Financial-compliance flavour. Delta: rule citation + risk classification; the red-team mock (#3 in module 07) is its adversarial run. #31 Legal Contract Review Copilot — Legal-contract flavour. Delta: clause extraction vs playbook, fallback language. Same spine. #47 Claims-Processing Assistant — Question-bank claims-processing version. Talking points only. #56 Deploying AI in a Highly Regulated Industry — Question-bank 'regulated industry' prompt. The anchor's PHI/consent/audit answer covers it. #89 Correct answer with misleading citations — Incident: correct answer, wrong citation (legal). Citation verification against the retrieval set, passage-level anchors. #92 PDF parser drops critical tables during policy ingestion — Incident: PDF parser drops tables. Ingestion QA: table-aware parsing, sampled extraction audits, parser version in traces. | H9: G08_Document_Review_Copilot/ | I9: https://forward-deployed-sigma.vercel.app/modules/15-fde-case-studies/knowledge-retrieval/document-review-copilot
A10: G09 Enterprise coding assistant | B10: 3 | C10: AI-Powered Coding Assistant (Copilot-class, < 300 ms) | D10: #3, #51 | E10: Copilot-class assistant grounded in private repos under a tight latency budget. | F10: #51 Enterprise AI Coding Assistant — Question-bank version. Talking points only. | H10: G09_Enterprise_Coding_Assistant/ | I10: https://forward-deployed-sigma.vercel.app/modules/15-fde-case-studies/agents-that-act/enterprise-coding-assistant
A11: G10 High-volume batch / document pipeline | B11: 21 | C11: High-Volume Batch Inference System (book ch 10) | D11: #21, #49, #42, #116 | E11: Nightly or bulk processing of millions of items under rate and cost limits; the target is replayability and recovery when behind. | F11: #49 Enterprise Document-Processing Platform — Extraction-platform framing (bank, millions of documents). Delta: extraction schema + QA sampling. #42 Document summarization pipeline for batch processing — Cost angle: nightly PDF summarization too expensive. Prepare tiering/caching/truncation answer. #116 Batch embedding job became too expensive — §15 scenario 13: batch embedding job too expensive. Content hashing, changed-only, cheaper embedding model, off-peak. | H11: G10_High_Volume_Batch_Pipeline/ | I11: https://forward-deployed-sigma.vercel.app/modules/15-fde-case-studies/platforms-and-scale/high-volume-batch-pipeline
A12: G11 Deep research agent | B12: 10 | C12: Deep Research Agent at consumer scale | D12: #10, #12, #103 | E12: Read-only, citation-grounded research agent at ~100K daily users. | F12: #12 The Research Platform — The same product as a deployed AWS/LangGraph system. Delta: infra layers (gateway, guardrails, pgvector, PyRIT). Read once as proof. #103 Research system with a supervisor and workers — Study-guide mock (multi-agent): supervisor plans N queries, workers run in parallel, synthesiser merges; hop cap and per-run budget. Implementation view of the anchor. | H12: G11_Deep_Research_Agent/ | I12: https://forward-deployed-sigma.vercel.app/modules/15-fde-case-studies/knowledge-retrieval/deep-research-agent
A13: G12 Delivery framework: scoping doc to deployed agent in two weeks | B13: 9 | C13: Scoping Doc to Deployed Agent in Two Weeks (delivery framework) | D13: #9, #65 | E13: Not a system design but a delivery-process case; both members use Northwind Logistics support triage. | F13: #65 Northwind Logistics — Tier-1 support triage agent, scoping to production in two weeks — Module 10 running case + the AI_Engineer interview script and code project. Same content in prose form. | H13: G12_Scoping_To_Deployed_Agent/ | I13: https://forward-deployed-sigma.vercel.app/modules/15-fde-case-studies/delivery-evaluation-operations/scoping-to-deployed-agent
A14: G13 Evaluation and release gating | B14: 20 | C14: LLM Evaluation and Release-Gating Platform (book ch 9) | D14: #20, #55, #52, #91, #120 | E14: How a change is proven safe to release: gates, thresholds, overrides, regression detection. | F14: #55 Build an Evaluation Strategy for an AI Application — Question-bank 'build an eval strategy'. The anchor's evidence/threshold answer covers it. #52 The Model Got Worse After an Upgrade — Question-bank 'model got worse after upgrade'. Answer = the gate the anchor designs, applied retroactively. #91 Model regression missed by a weak evaluation suite — Incident: model regression passed offline evals (sales copilot). The gate must test unsupported claims, not fluency; add claim-grounding checks. #120 Costs are fine but the eval bill tripled — Addition: eval bill tripled. LLM-as-judge is inference: stratified sample, cheap judge with strong-judge audit, deltas only. | H14: G13_Evaluation_And_Release_Gating/ | I14: https://forward-deployed-sigma.vercel.app/modules/15-fde-case-studies/delivery-evaluation-operations/evaluation-and-release-gating
... A21: G16 Real-time call assistant | B21: 59 | C21: AI Assistant for Sales or Customer-Service Calls | D21: #59, #43 | E21: Transcribe live sales/service calls, summarise, extract actions, update CRM, under a sub-3-second target. | F21: #43 Real-time sales assistant, sub-3-second response — Latency angle (sub-3 s during the call). Prepare streaming ASR + incremental context answer. | H21: G16_Real_Time_Call_Assistant/ | I21: https://forward-deployed-sigma.vercel.app/modules/15-fde-case-studies/agents-that-act/real-time-call-assistant
A23: Standalone (no sibling worth merging) | D23: #4, #14, #19, #23, #25, #26, #60, #61, #62, #67, #68, #69, #80, #98, #100 | E23: Grouped nothing here; each has a different core problem. #67/#68/#69 share the decomposition METHOD (framework in the reported-prompts HTML, section 4) but not the case. See the Prep note column on the Case Studies tab. | H23: Standalone/ — one folder per case (#67/#68/#69 share one pack); exact path in the Case Studies tab, Prep pack column | I23: https://forward-deployed-sigma.vercel.app/modules/15-fde-case-studies

Sheet Drill Add-ons
A1: Cost/latency drills — one 10-minute add-on per anchor
A2: Shared by all seven — the four verbs that generate every strong answer: | B2: measure (trace/attribute first) → route (match model and path to risk) → bound (steps, tokens, top-k, timeouts, budgets) → cache safely (tenant + permission + version in the key)
A3: Shared by all seven — the 60-second delivery structure: | B3: 1 frame the business impact · 2 decompose the path (retrieval, rerank, inference, tools, retries, cache, post-processing) · 3 name the largest measured driver · 4 fix safely · 5 prove with before/after (P95, cost/request, quality evals, cache hit rate) · 6 prevent recurrence (budgets, alerts, regression checks, per-tenant dashboard)
A4: Source: | B4: Study_Guides/Cost_Latency_Optimization/CRAM_SHEET_S15_S16.md §16 (cases) and §4 (weak vs strong); drill deck: Cost_Latency_Drills_S15_S16.html
A6: # | B6: Drill | C6: Attach to anchor | D6: Dominant driver | E6: Cheapest lever first | F6: Metric that proves it | G6: Do not | H6: 60-second line | I6: Kind
A7: 38 | B7: Legal RAG under strict cost limits | C7: #15 Enterprise Knowledge Assistant (G01) | D7: Input tokens: whole corpus stuffed into long context, plus unconditional rerank | E7: Calibrated top-k with metadata filters; rerank only ambiguous queries; route simple clause lookups to a mid-tier model | F7: Cost per request; Recall@k; citation correctness; retrieval vs model latency split | G7: Strongest model with all documents in context every time | H7: Legal quality forces citations and escalation, budget forces top-k and routing, the 8-second target rules out heavy rerank on every query. Pilot on a limited document set with cost instrumented from day one. | I7: Playbook
A8: 39 | B8: Support chatbot, 10k daily users | C8: #18 AI Customer-Support Automation (G02) | D8: Model spend on repeated FAQ traffic that needs no LLM | E8: Intent router in front; permission-aware semantic cache for safe FAQs; small model for classification; tools only for account data | F8: Cost per resolved ticket; deflection rate; cache hit rate; P95 latency | G8: Keep the same model and hope browser caching helps | H8: Reduce cost by workflow, not across the board. Cache the FAQ path, route by intent, protect the account-data path. | I8: Playbook
A9: 40 | B9: Latency of an agentic CRM assistant | C9: #28 Sales Copilot (G05) | D9: Agent steps and serial tool calls | E9: Trace first; cap steps; parallelise read-only calls; precompute account snapshots; deterministic route for common requests | F9: Agent step count; tool latency; cache hit rate; timeout rate | G9: Swap to a faster model without reading a trace | H9: Replace the open-ended agent loop with a bounded execution graph. Common CRM operations are deterministic and cache-backed; the agent handles only the ambiguous next step. | I9: Playbook
A10: 41 | B10: Multi-tenant platform with per-customer budgets | C10: #16 Secure Multi-Tenant AI Platform (G07) | D10: Uncontrolled spend with no attribution, and a shared cache that leaks across tenants | E10: Tenant-aware gateway with budget check before the model call; cache keyed on tenant + permission signature; quota alerts | F10: Cost per tenant; quota usage; cross-tenant access tests; cache hit rate by tenant | G10: Global token limit plus one shared cache | H10: Make tenant_id and permission_signature first-class in every service. Budgets are contractual, so meter before the call, not after. | I10: Playbook
A11: 42 | B11: Nightly PDF summarisation too expensive | C11: #21 High-Volume Batch Inference (G10) | D11: Reprocessing unchanged documents on a premium model | E11: Content hash and change detection; dedupe; cheaper model in batch mode; sampled strong-model audit | F11: Changed ratio; cost per document; queue depth; eval score on the sample | G11: Run every PDF through the premium model every night | H11: Never reprocess an unchanged document without a reason. Batch buys throughput not latency, so quality is proven by sampling. | I11: Playbook
A12: 43 | B12: Real-time sales assistant, sub-3 seconds | C12: #59 Call Assistant (G16) | D12: Synchronous live CRM lookup plus a large model inside the 3-second window | E12: Precompute account context before the call; small prompt with a fast model streamed during; enrichment and CRM update async after | F12: First-token latency; total latency; precompute hit rate; user accept rate; timeout rate | G12: Large model with a live CRM lookup per request | H12: Sub-3 seconds is a workflow design problem, not a model choice. Split before, during and after the call. | I12: Playbook
A13: 44 | B13: Incident: LLM costs exploded after launch | C13: #24 Observability for a Customer-Facing AI App (G14) | D13: Unknown until attributed: usually retries, agent loops, batch or eval jobs, or an integration loop | E13: Spend circuit breaker first; attribute by tenant and feature; cap output; pause batch and eval; downgrade premium routing; tenant quotas; then root cause | F13: Cost per minute; tokens per request; model distribution; retry count; agent steps; tenant usage | G13: Kill the whole feature without diagnosis | H13: Contain, attribute, then diagnose. Keep low-cost safe paths online while disabling runaway paths. The real lesson is that budget guardrails must exist before launch. | I13: Playbook
A15: Self-drills for the nine anchors with no playbook case — written for this index from the 8 drivers, not taken from the playbook
A16: 22 | B16: Self-drill: tool-using agent gets slow and expensive | C16: #22 Tool-Using Agent with Safety Controls (G03) | D16: Agent steps and tool calls, plus retries after failed or rejected actions | E16: Bound steps per request; deterministic route for known intents; cache read-only tool results within the request; approval gate as the loop breaker | F16: Steps per request; tool latency; retry count; cost per request | G16: Give the loop a bigger model and a longer budget | H16: An agent that acts must be bounded before it is optimised. Cap the steps, make the common paths deterministic, and let the approval gate stop the loop. | I16: Self-drill
A17: 11 | B17: Self-drill: incident agent misses its 30-second floor | C17: #11 Incident Response Agent for SRE (G04) | D17: Input tokens: raw logs, traces and deploy diffs stuffed into context, then serial diagnostic steps | E17: Pre-aggregate telemetry before the model sees it; parallel read-only diagnostics; small model for correlation, strong model only for the hypothesis; cap steps | F17: Input tokens per request; time to first hypothesis; step count; timeout rate | G17: Feed the model everything and ask it to find the needle | H17: Under a latency floor the win is in what you do not send. Summarise telemetry first, run diagnostics in parallel, and spend the strong model on the hypothesis only. | I17: Self-drill
A18: 17 | B18: Self-drill: NL-to-SQL cost climbs with every failed query | C18: #17 Natural-Language-to-SQL Assistant (G06) | D18: Retries on invalid or wrong SQL, and the full schema carried as input tokens on every call | E18: Semantic layer so the prompt carries metrics not tables; validate and dry-run SQL before execution; cache metric definitions and recurring executive questions; small model for routing | F18: First-try success rate; retry rate; cost per query; P95 latency | G18: Retry with a stronger model until the SQL runs | H18: Valid SQL that answers the wrong question is the failure, so the fix is a semantic layer and validation, not more retries. That also removes the schema from every prompt. | I18: Self-drill
A19: 30 | B19: Self-drill: document review copilot too expensive per file | C19: #30 Healthcare Prior Authorization Assistant (G08) | D19: Input tokens on long documents, and every page going through the strongest model | E19: Extract only the relevant sections first; dedupe templated documents by hash; cheap model for extraction, strong model only on flagged risk; batch the non-urgent queue off-peak | F19: Cost per document; tokens per document; escalation rate; extraction accuracy on a sampled audit | G19: Send the whole document to the premium model every time | H19: Extraction is cheap, judgement is expensive. Route pages to extraction, route only the flagged risks to the strong model, and prove quality by sampling. | I19: Self-drill
A20: 3 | B20: Self-drill: coding assistant at under 300 ms | C20: #3 AI-Powered Coding Assistant (G09) | D20: Output tokens and context size inside a hard latency budget | E20: Context funnel so only nearest files enter the prompt; prompt-prefix caching; small fast model for completions, strong model only for explicit refactors; cap completion length | F20: First-token latency; tokens per completion; acceptance rate; cache hit rate | G20: One big model for completions and chat alike | H20: Completions are a latency product. Funnel the context, cache the prefix, keep completions short and fast, and reserve the strong model for the tasks a user waits for. | I20: Self-drill
A21: 10 | B21: Self-drill: research agent cost per report | C21: #10 Deep Research Agent (G11) | D21: Agent steps as search rounds, and long-context synthesis over every source found | E21: Cap search rounds; dedupe sources before reading; compress evidence before synthesis; cache finished reports by topic (the deployed research platform already does this) | F21: Searches per report; cost per report; cache hit rate; tokens into synthesis | G21: Let the agent search until it is satisfied | H21: Cost here is search fan-out times synthesis context. Bound the rounds, dedupe, compress, and never research the same topic twice. | I21: Self-drill
A22: 9 | B22: Self-drill: pilot spend during a two-week delivery | C22: #9 Scoping Doc to Deployed Agent in Two Weeks (G12) | D22: Evaluation and logging overhead during the pilot, plus an unbounded agent in front of real tickets | E22: Agree cost per resolved ticket at intake alongside the quality metrics; sampled evals not full-corpus; step and token caps from day one; budget alert per pilot | F22: Cost per resolved ticket vs the intake baseline; eval spend per day; P95 | G22: Instrument cost after the pilot proves value | H22: Cost is a success metric agreed at intake, not a cleanup after go-live. Cap the agent, sample the evals, and report cost per resolved ticket in the same dashboard as quality. | I22: Self-drill
A23: 20 | B23: Self-drill: evaluation gate is too expensive to run per release | C23: #20 LLM Evaluation and Release-Gating Platform (G13) | D23: Batch and evaluation pipeline spend: LLM-as-judge over the full suite on every change | E23: Sample the suite for smoke tests; cheap judge first, strong judge only on failures and disagreements; cache judged pairs by prompt version; full suite only at the release gate | F23: Eval cost per release; judge agreement rate; time to gate; regressions caught per dollar | G23: Run the full strong-judge suite on every commit | H23: A gate nobody can afford gets bypassed. Tier the judges, sample on every change, run the full suite only where a release decision is made. | I23: Self-drill
A24: 8 | B24: Self-drill: user-built automations run away with spend | C24: #8 Agent Platform for Non-Technical Users (G15) | D24: Retries and loops in user-authored automations, with no budget owner per tenant | E24: Per-automation step and token caps; per-tenant budgets with a circuit breaker; idempotency keys on every action; deterministic events instead of free-text triggers | F24: Cost per automation run; steps per run; runaway kills per day; cost per tenant | G24: Trust users to write bounded workflows | H24: Non-technical users will build loops. The platform bounds them: caps per run, a budget per tenant, idempotent actions, and a breaker that trips before the invoice does. | I24: Self-drill

Sheet Case Studies
A1: # | B1: Category | C1: Group | D1: Role in group | E1: Prep note (delta vs anchor) | F1: Case study | G1: Collection | H1: Primary path (relative to 06_Interview_Prep/) | I1: Answer key / paired doc | J1: Also appears in | K1: Formats | L1: Tracked in git | M1: Notes | N1: Prep pack (relative to Case_Study_Groups/) | O1: Site page (Forward Deployed)
A2: 1 | B2: Worked system design | C2: G03 Tool-using agent acting across enterprise systems | D2: Covered by anchor — read delta only | E2: Casebook design over 100+ internal apps. Delta: REST vs function-calling vs MCP as layers, tool registry at scale, identity propagation. Read that layering section. | F2: Enterprise AI Assistant over 100+ internal applications | G2: Handbook Module 09 — AI System Design Casebook | H2: Handbook/09_AI_System_Design_Casebook/01_Enterprise_AI_Assistant.md | J2: FDE/System_Design and Delivery/5. Enterprise AI Assistant Design.md (older source, md + html) | K2: md (+ html in older copy) | L2: Yes | M2: REST vs function calling vs MCP vs agent frameworks as layers; tool registry at scale; identity propagation | N2: G03_Tool_Using_Agent_With_Safety_Controls/ | O2: https://forward-deployed-sigma.vercel.app/modules/15-fde-case-studies/agents-that-act/tool-using-agent-with-safety-controls
A3: 2 | B3: Worked system design | C3: G02 Customer-support automation | D3: Covered by anchor — read delta only | E3: Casebook worked design at 1M conversations/day. Delta: three memory layers, planner justification, model routing. Read the memory + routing sections. | F3: Customer Support Assistant (Einstein + Zendesk, 1M conversations/day) | G3: Handbook Module 09 — AI System Design Casebook | H3: Handbook/09_AI_System_Design_Casebook/02_Customer_Support_Assistant.md | J3: FDE/System_Design and Delivery/6. Customer Support AI Assistant Design.md (older source, md + html) | K3: md (+ html in older copy) | L3: Yes | M3: RAG vs tool calling; when a planner is justified; three memory layers; human approval; model routing | N3: G02_Customer_Support_Automation/ | O3: https://forward-deployed-sigma.vercel.app/modules/15-fde-case-studies/agents-that-act/customer-support-automation
A4: 3 | B4: Worked system design | C4: G09 Enterprise coding assistant | D4: ANCHOR — prepare this | E4: Anchor: casebook worked design (context funnel, cache first, model routing, decomposed latency budget). Cost/latency self-drill on the Drill Add-ons tab. | F4: AI-Powered Coding Assistant (Copilot-class, < 300 ms) | G4: Handbook Module 09 — AI System Design Casebook | H4: Handbook/09_AI_System_Design_Casebook/03_Coding_Assistant.md | J4: FDE/System_Design and Delivery/7. AI Powered Coding Assistant Design.md (older source, md + html) | K4: md (+ html in older copy) | L4: Yes | M4: Context engineering as a funnel; cache first; model routing by task; decomposed latency budget | N4: G09_Enterprise_Coding_Assistant/ | O4: https://forward-deployed-sigma.vercel.app/modules/15-fde-case-studies/agents-that-act/enterprise-coding-assistant
A5: 4 | B5: Worked system design | C5: — standalone | D5: Prepare on its own | E5: Recruiting platform — structured extraction + explainable ranking + fairness. No sibling. | F5: AI-Powered Recruiting Platform (resume to hiring decision) | G5: Handbook Module 09 — AI System Design Casebook | H5: Handbook/09_AI_System_Design_Casebook/04_Recruiting_Platform.md | J5: FDE/System_Design and Delivery/8. AI Powered Recruiting Platform Design.md (older source, md + html) | K5: md (+ html in older copy) | L5: Yes | M5: Structured extraction as the seam; explainable ranking; AI judge that does not decide; fairness as a control | N5: Standalone/04_Recruiting_Platform/ [copied source files (folder)] | O5: https://forward-deployed-sigma.vercel.app/modules/15-fde-case-studies/standalone-designs/recruiting-platform
A6: 5 | B6: Worked system design | C6: G17 Logistics exception handling / shipment rerouting agent | D6: ANCHOR — prepare this | E6: Anchor: casebook worked design (policy gate with customs first, streaming + batch unified, shared control plane / regional data planes, low-DAU high-stakes sizing). | F6: AI Logistics Exception-Handling Assistant (the FDE round) | G6: Handbook Module 09 — AI System Design Casebook | H6: Handbook/09_AI_System_Design_Casebook/05_Logistics_Exception_Handling.md | J6: FDE/System_Design and Delivery/AI Logistics Exception-Handling Assistant Design.md; Mock - AI Exception-Handling Assistant.md (older source, md + html) | K6: md (+ html in older copy) | L6: Yes | M6: Clarifying questions; streaming + batch unified; Policy Gate; shared control plane, regional data planes | N6: G17_Logistics_Exception_Handling/ | O6: https://forward-deployed-sigma.vercel.app/modules/15-fde-case-studies/agents-that-act/logistics-exception-handling
A7: 6 | B7: Worked system design | C7: G01 Enterprise knowledge assistant (permission-aware RAG) | D7: Covered by anchor — read delta only | E7: 60-min whiteboard script of the same design. Use it to rehearse timing; content is the anchor's. | F7: Enterprise RAG with Access Control | G7: Handbook Module 09 — 60-minute whiteboard scripts | H7: Handbook/09_AI_System_Design_Casebook/whiteboard_scripts/01_Enterprise_RAG_With_Access_Control.md | K7: md | L7: Yes | M7: Minute-by-minute performance script. Built in Handbook Module 04 | N7: G01_Enterprise_Knowledge_Assistant/ | O7: https://forward-deployed-sigma.vercel.app/modules/15-fde-case-studies/knowledge-retrieval/enterprise-knowledge-assistant
A8: 7 | B8: Worked system design | C8: G01 Enterprise knowledge assistant (permission-aware RAG) | D8: Covered by anchor — read delta only | E8: Databricks/Lakehouse variant. Delta: leads with the Vector Search trap and Unity Catalog ACLs. Worth 15 min given your employer. | F8: Enterprise RAG on Databricks (Lakehouse audience) | G8: Handbook Module 09 — 60-minute whiteboard scripts | H8: Handbook/09_AI_System_Design_Casebook/whiteboard_scripts/02_Enterprise_RAG_On_Databricks.md | K8: md | L8: Yes | M8: Minute-by-minute performance script. Built in Handbook Module 08 doc 3 | N8: G01_Enterprise_Knowledge_Assistant/ | O8: https://forward-deployed-sigma.vercel.app/modules/15-fde-case-studies/knowledge-retrieval/enterprise-knowledge-assistant
A9: 8 | B9: Worked system design | C9: G15 Agent platform for non-technical users | D9: ANCHOR — prepare this | E9: Anchor: 60-min whiteboard script. Cost/latency self-drill on the Drill Add-ons tab. | F9: Agent Platform for Non-Technical Users (multi-channel workflow automation) | G9: Handbook Module 09 — 60-minute whiteboard scripts | H9: Handbook/09_AI_System_Design_Casebook/whiteboard_scripts/03_Agent_Platform_For_Non_Technical_Users.md | K9: md | L9: Yes | M9: Minute-by-minute performance script. Built in Handbook Module 05 | N9: G15_Agent_Platform_For_Non_Technical_Users/ | O9: https://forward-deployed-sigma.vercel.app/modules/15-fde-case-studies/platforms-and-scale/agent-platform-for-non-technical-users
A10: 9 | B10: Worked system design | C10: G12 Delivery framework: scoping doc to deployed agent in two weeks | D10: ANCHOR — prepare this | E10: Anchor: 60-min whiteboard script. Cost/latency self-drill on the Drill Add-ons tab. | F10: Scoping Doc to Deployed Agent in Two Weeks (delivery framework) | G10: Handbook Module 09 — 60-minute whiteboard scripts | H10: Handbook/09_AI_System_Design_Casebook/whiteboard_scripts/04_Scoping_Doc_To_Deployed_Agent_In_Two_Weeks.md | K10: md | L10: Yes | M10: Minute-by-minute performance script. Built in Handbook Module 10 | N10: G12_Scoping_To_Deployed_Agent/ | O10: https://forward-deployed-sigma.vercel.app/modules/15-fde-case-studies/delivery-evaluation-operations/scoping-to-deployed-agent
A11: 10 | B11: Worked system design | C11: G11 Deep research agent | D11: ANCHOR — prepare this | E11: Anchor: worked design with the script and the arithmetic. Cost/latency self-drill on the Drill Add-ons tab. | F11: Deep Research Agent at consumer scale | G11: Cracking Agentic AI System Design Interviews — Ch 28 | H11: FDE/Cracking_Agentic_AI_System_Design_Interviews/ch28_system_design_interview.md | K11: md + html | L11: Yes | M11: Worked Design One. Ch 23 (system design patterns) is the vocabulary it uses. | N11: G11_Deep_Research_Agent/ | O11: https://forward-deployed-sigma.vercel.app/modules/15-fde-case-studies/knowledge-retrieval/deep-research-agent
A12: 11 | B12: Worked system design | C12: G04 SRE / incident-response agent | D12: ANCHOR — prepare this | E12: Anchor: full worked design with the arithmetic (write-capable, 30-second latency floor). Cost/latency self-drill on the Drill Add-ons tab. | F12: Incident Response Agent for an SRE team | G12: Cracking Agentic AI System Design Interviews — Ch 28 | H12: FDE/Cracking_Agentic_AI_System_Design_Interviews/ch28_system_design_interview.md | K12: md + html | L12: Yes | M12: Worked Design Two. | N12: G04_SRE_Incident_Response_Agent/ | O12: https://forward-deployed-sigma.vercel.app/modules/15-fde-case-studies/agents-that-act/sre-incident-response-agent
A13: 12 | B13: Worked system design | C13: G11 Deep research agent | D13: Covered by anchor — read delta only | E13: The same product as a deployed AWS/LangGraph system. Delta: infra layers (gateway, guardrails, pgvector, PyRIT). Read once as proof. | F13: The Research Platform (multi-agent) | G13: Handbook Module 07 — Multi-Agent Systems | H13: Handbook/07_Multi_Agent_Systems/04_Case_Study_Research_Platform.md | K13: md | L13: Yes | N13: G11_Deep_Research_Agent/ | O13: https://forward-deployed-sigma.vercel.app/modules/15-fde-case-studies/knowledge-retrieval/deep-research-agent
A14: 13 | B14: Worked system design | C14: G06 Natural language over governed data (NL-to-SQL, KPI copilot) | D14: Covered by anchor — read delta only | E14: Your AIA governed-data assistant told as architecture evolution (supervisor → deep agent). Delta: multi-agent evolution; also your STAR story. | F14: From Supervisor to Deep Agent (multi-agent) | G14: Handbook Module 07 — Multi-Agent Systems | H14: Handbook/07_Multi_Agent_Systems/05_Case_Study_Supervisor_To_Deep_Agent.md | K14: md | L14: Yes | N14: G06_NL_Over_Governed_Data/ | O14: https://forward-deployed-sigma.vercel.app/modules/15-fde-case-studies/knowledge-retrieval/nl-over-governed-data
A15: 14 | B15: Worked system design | C15: — standalone | D15: Prepare on its own | E15: Foundations worked example for the 12-part framework. No sibling. | F15: The Travel Agent (12-part framework worked example) | G15: Handbook Module 02 — System Design Fundamentals | H15: Handbook/02_System_Design_Fundamentals/04_Worked_Example_Travel_Agent.md | J15: FDE/System_Design and Delivery/1. System Design Overview.md (source) | K15: md | L15: Yes | M15: Foundations-level worked example. | N15: Standalone/14_Travel_Agent_Worked_Example/ [copied source files (folder)] | O15: https://forward-deployed-sigma.vercel.app/modules/15-fde-case-studies/standalone-designs/travel-agent-worked-example
A16: 15 | B16: Worksheet + answer key | C16: G01 Enterprise knowledge assistant (permission-aware RAG) | D16: ANCHOR — prepare this | E16: Anchor: bespoke worksheet + answer key + V1/V2 tutorials. Then rehearse #6 aloud against the clock. | F16: Enterprise Knowledge Assistant with RAG (book ch 1) | G16: FDE System Design Interview — 20 Scenarios (Version 3) | H16: FDE/FDE_System_Design_Interview_20_Scenarios/Version_3/01_enterprise_knowledge_assistant_rag.md | I16: FDE/FDE_System_Design_Interview_20_Scenarios/Version_3/answer_keys/01_enterprise_knowledge_assistant_rag_answer_key.md | J16: V1 long tutorial: FDE/FDE_System_Design_Interview_20_Scenarios/Version_1/chapter-1-enterprise-knowledge-assistant-rag-tutorial.md | V2 cram: FDE/FDE_System_Design_Interview_20_Scenarios/Version_2/chapter-1-enterprise-knowledge-assistant-rag-tutorial_v2.md | Site: site/content/modules/01-customer-discovery-and-decomposition/system-design/worksheets/enterprise-knowledge-assistant-rag.md | K16: worksheet md + answer key md + V1/V2 tutorials + site page | L16: Yes | M16: Source: The Forward Deployed Engineer System Design Interview (Kindle). Ch 21 V1 also has an uncondensed tutorial. | N16: G01_Enterprise_Knowledge_Assistant/ | O16: https://forward-deployed-sigma.vercel.app/modules/15-fde-case-studies/knowledge-retrieval/enterprise-knowledge-assistant
A17: 16 | B17: Worksheet + answer key | C17: G07 Secure multi-tenant AI platform | D17: ANCHOR — prepare this | E17: Anchor: bespoke worksheet + answer key. | F17: Secure Multi-Tenant AI Platform (book ch 2) | G17: FDE System Design Interview — 20 Scenarios (Version 3) | H17: FDE/FDE_System_Design_Interview_20_Scenarios/Version_3/02_secure_multi_tenant_ai_platform.md | I17: FDE/FDE_System_Design_Interview_20_Scenarios/Version_3/answer_keys/02_secure_multi_tenant_ai_platform_answer_key.md | J17: V1 long tutorial: FDE/FDE_System_Design_Interview_20_Scenarios/Version_1/chapter-2-secure-multi-tenant-ai-platform-tutorial.md | V2 cram: FDE/FDE_System_Design_Interview_20_Scenarios/Version_2/chapter-2-secure-multi-tenant-ai-platform-tutorial_v2.md | Site: site/content/modules/01-customer-discovery-and-decomposition/system-design/worksheets/secure-multi-tenant-ai-platform.md | K17: worksheet md + answer key md + V1/V2 tutorials + site page | L17: Yes | M17: Source: The Forward Deployed Engineer System Design Interview (Kindle). Ch 21 V1 also has an uncondensed tutorial. | N17: G07_Secure_Multi_Tenant_AI_Platform/ | O17: https://forward-deployed-sigma.vercel.app/modules/15-fde-case-studies/platforms-and-scale/secure-multi-tenant-ai-platform
A18: 17 | B18: Worksheet + answer key | C18: G06 Natural language over governed data (NL-to-SQL, KPI copilot) | D18: ANCHOR — prepare this | E18: Anchor: bespoke worksheet + answer key; semantic layer, metric ownership, ambiguity handling. Cost/latency self-drill on the Drill Add-ons tab. | F18: Natural-Language-to-SQL Analytics Assistant (book ch 3) | G18: FDE System Design Interview — 20 Scenarios (Version 3) | H18: FDE/FDE_System_Design_Interview_20_Scenarios/Version_3/03_natural_language_to_sql_analytics_assistant.md | I18: FDE/FDE_System_Design_Interview_20_Scenarios/Version_3/answer_keys/03_natural_language_to_sql_analytics_assistant_answer_key.md | J18: V1 long tutorial: FDE/FDE_System_Design_Interview_20_Scenarios/Version_1/chapter-3-natural-language-to-sql-analytics-assistant-tutorial.md | V2 cram: FDE/FDE_System_Design_Interview_20_Scenarios/Version_2/chapter-3-natural-language-to-sql-analytics-assistant-tutorial_v2.md | Site: site/content/modules/01-customer-discovery-and-decomposition/system-design/worksheets/natural-language-to-sql-analytics-assistant.md | K18: worksheet md + answer key md + V1/V2 tutorials + site page | L18: Yes | M18: Source: The Forward Deployed Engineer System Design Interview (Kindle). Ch 21 V1 also has an uncondensed tutorial. | N18: G06_NL_Over_Governed_Data/ | O18: https://forward-deployed-sigma.vercel.app/modules/15-fde-case-studies/knowledge-retrieval/nl-over-governed-data
A19: 18 | B19: Worksheet + answer key | C19: G02 Customer-support automation | D19: ANCHOR — prepare this | E19: Anchor: bespoke worksheet + answer key + tutorials; covers autonomous vs approved actions and handoff. | F19: AI Customer-Support Automation (book ch 4) | G19: FDE System Design Interview — 20 Scenarios (Version 3) | H19: FDE/FDE_System_Design_Interview_20_Scenarios/Version_3/04_ai_customer_support_automation.md | I19: FDE/FDE_System_Design_Interview_20_Scenarios/Version_3/answer_keys/04_ai_customer_support_automation_answer_key.md | J19: V1 long tutorial: FDE/FDE_System_Design_Interview_20_Scenarios/Version_1/chapter-4-ai-customer-support-automation-tutorial.md | V2 cram: FDE/FDE_System_Design_Interview_20_Scenarios/Version_2/chapter-4-ai-customer-support-automation-tutorial_v2.md | Site: site/content/modules/01-customer-discovery-and-decomposition/system-design/worksheets/ai-customer-support-automation.md | K19: worksheet md + answer key md + V1/V2 tutorials + site page | L19: Yes | M19: Source: The Forward Deployed Engineer System Design Interview (Kindle). Ch 21 V1 also has an uncondensed tutorial. | N19: G02_Customer_Support_Automation/ | O19: https://forward-deployed-sigma.vercel.app/modules/15-fde-case-studies/agents-that-act/customer-support-automation
A20: 19 | B20: Worksheet + answer key | C20: — standalone | D20: Prepare on its own | E20: Air-gapped — the boundary is the design. No sibling. | F20: AI System for an Air-Gapped Environment (book ch 7) | G20: FDE System Design Interview — 20 Scenarios (Version 3) | H20: FDE/FDE_System_Design_Interview_20_Scenarios/Version_3/07_ai_system_for_an_air_gapped_environment.md | I20: FDE/FDE_System_Design_Interview_20_Scenarios/Version_3/answer_keys/07_ai_system_for_an_air_gapped_environment_answer_key.md | J20: V1 long tutorial: FDE/FDE_System_Design_Interview_20_Scenarios/Version_1/chapter-7-ai-system-for-an-air-gapped-environment-tutorial.md | V2 cram: FDE/FDE_System_Design_Interview_20_Scenarios/Version_2/chapter-7-ai-system-for-an-air-gapped-environment-tutorial_v2.md | Site: site/content/modules/01-customer-discovery-and-decomposition/system-design/worksheets/ai-system-for-an-air-gapped-environment.md | K20: worksheet md + answer key md + V1/V2 tutorials + site page | L20: Yes | M20: Source: The Forward Deployed Engineer System Design Interview (Kindle). Ch 21 V1 also has an uncondensed tutorial. | N20: Standalone/19_Air_Gapped_AI_System/ [copied source files (folder)] | O20: https://forward-deployed-sigma.vercel.app/modules/15-fde-case-studies/standalone-designs/air-gapped-ai-system
A21: 20 | B21: Worksheet + answer key | C21: G13 Evaluation and release gating | D21: ANCHOR — prepare this | E21: Anchor: bespoke worksheet + answer key. Cost/latency self-drill on the Drill Add-ons tab. | F21: LLM Evaluation and Release-Gating Platform (book ch 9) | G21: FDE System Design Interview — 20 Scenarios (Version 3) | H21: FDE/FDE_System_Design_Interview_20_Scenarios/Version_3/09_llm_evaluation_and_release_gating_platform.md | I21: FDE/FDE_System_Design_Interview_20_Scenarios/Version_3/answer_keys/09_llm_evaluation_and_release_gating_platform_answer_key.md | J21: V1 long tutorial: FDE/FDE_System_Design_Interview_20_Scenarios/Version_1/chapter-9-llm-evaluation-and-release-gating-platform-tutorial.md | V2 cram: FDE/FDE_System_Design_Interview_20_Scenarios/Version_2/chapter-9-llm-evaluation-and-release-gating-platform-tutorial_v2.md | Site: site/content/modules/01-customer-discovery-and-decomposition/system-design/worksheets/llm-evaluation-and-release-gating-platform.md | K21: worksheet md + answer key md + V1/V2 tutorials + site page | L21: Yes | M21: Source: The Forward Deployed Engineer System Design Interview (Kindle). Ch 21 V1 also has an uncondensed tutorial. | N21: G13_Evaluation_And_Release_Gating/ | O21: https://forward-deployed-sigma.vercel.app/modules/15-fde-case-studies/delivery-evaluation-operations/evaluation-and-release-gating
A22: 21 | B22: Worksheet + answer key | C22: G10 High-volume batch / document pipeline | D22: ANCHOR — prepare this | E22: Anchor: bespoke worksheet + answer key (100M records before 6 a.m.). | F22: High-Volume Batch Inference System (book ch 10) | G22: FDE System Design Interview — 20 Scenarios (Version 3) | H22: FDE/FDE_System_Design_Interview_20_Scenarios/Version_3/10_high_volume_batch_inference_system.md | I22: FDE/FDE_System_Design_Interview_20_Scenarios/Version_3/answer_keys/10_high_volume_batch_inference_system_answer_key.md | J22: V1 long tutorial: FDE/FDE_System_Design_Interview_20_Scenarios/Version_1/chapter-10-high-volume-batch-inference-system-tutorial.md | V2 cram: FDE/FDE_System_Design_Interview_20_Scenarios/Version_2/chapter-10-high-volume-batch-inference-system-tutorial_v2.md | Site: site/content/modules/01-customer-discovery-and-decomposition/system-design/worksheets/high-volume-batch-inference-system.md | K22: worksheet md + answer key md + V1/V2 tutorials + site page | L22: Yes | M22: Source: The Forward Deployed Engineer System Design Interview (Kindle). Ch 21 V1 also has an uncondensed tutorial. | N22: G10_High_Volume_Batch_Pipeline/ | O22: https://forward-deployed-sigma.vercel.app/modules/15-fde-case-studies/platforms-and-scale/high-volume-batch-pipeline
A23: 22 | B23: Worksheet + answer key | C23: G03 Tool-using agent acting across enterprise systems | D23: ANCHOR — prepare this | E23: Anchor: bespoke worksheet + answer key; 'model proposes, never decides' plus rollback and money boundary. Cost/latency self-drill on the Drill Add-ons tab. | F23: Tool-Using AI Agent with Safety Controls (book ch 11) | G23: FDE System Design Interview — 20 Scenarios (Version 3) | H23: FDE/FDE_System_Design_Interview_20_Scenarios/Version_3/11_tool_using_ai_agent_with_safety_controls.md | I23: FDE/FDE_System_Design_Interview_20_Scenarios/Version_3/answer_keys/11_tool_using_ai_agent_with_safety_controls_answer_key.md | J23: V1 long tutorial: FDE/FDE_System_Design_Interview_20_Scenarios/Version_1/chapter-11-tool-using-ai-agent-with-safety-controls-tutorial.md | V2 cram: FDE/FDE_System_Design_Interview_20_Scenarios/Version_2/chapter-11-tool-using-ai-agent-with-safety-controls-tutorial_v2.md | Site: site/content/modules/01-customer-discovery-and-decomposition/system-design/worksheets/tool-using-ai-agent-with-safety-controls.md | K23: worksheet md + answer key md + V1/V2 tutorials + site page | L23: Yes | M23: Source: The Forward Deployed Engineer System Design Interview (Kindle). Ch 21 V1 also has an uncondensed tutorial. | N23: G03_Tool_Using_Agent_With_Safety_Controls/ | O23: https://forward-deployed-sigma.vercel.app/modules/15-fde-case-studies/agents-that-act/tool-using-agent-with-safety-controls
A24: 23 | B24: Worksheet + answer key | C24: — standalone | D24: Prepare on its own | E24: Reliable workflow orchestration — exactly-once business effect, compensation, days-long waits. Related to G03/G15 but a different problem. | F24: Reliable Workflow Orchestration System (book ch 13) | G24: FDE System Design Interview — 20 Scenarios (Version 3) | H24: FDE/FDE_System_Design_Interview_20_Scenarios/Version_3/13_reliable_workflow_orchestration_system.md | I24: FDE/FDE_System_Design_Interview_20_Scenarios/Version_3/answer_keys/13_reliable_workflow_orchestration_system_answer_key.md | J24: V1 long tutorial: FDE/FDE_System_Design_Interview_20_Scenarios/Version_1/chapter-13-reliable-workflow-orchestration-system-tutorial.md | V2 cram: FDE/FDE_System_Design_Interview_20_Scenarios/Version_2/chapter-13-reliable-workflow-orchestration-system-tutorial_v2.md | Site: site/content/modules/01-customer-discovery-and-decomposition/system-design/worksheets/reliable-workflow-orchestration-system.md | K24: worksheet md + answer key md + V1/V2 tutorials + site page | L24: Yes | M24: Source: The Forward Deployed Engineer System Design Interview (Kindle). Ch 21 V1 also has an uncondensed tutorial. | N24: Standalone/23_Reliable_Workflow_Orchestration/ [copied source files (folder)] | O24: https://forward-deployed-sigma.vercel.app/modules/15-fde-case-studies/standalone-designs/reliable-workflow-orchestration
A25: 24 | B25: Worksheet + answer key | C25: G14 Observability and production diagnosis | D25: ANCHOR — prepare this | E25: Anchor: bespoke worksheet + answer key. | F25: Observability for a Customer-Facing AI Application (book ch 15) | G25: FDE System Design Interview — 20 Scenarios (Version 3) | H25: FDE/FDE_System_Design_Interview_20_Scenarios/Version_3/15_observability_customer_facing_ai_application.md | I25: FDE/FDE_System_Design_Interview_20_Scenarios/Version_3/answer_keys/15_observability_customer_facing_ai_application_answer_key.md | J25: V1 long tutorial: FDE/FDE_System_Design_Interview_20_Scenarios/Version_1/chapter-15-observability-customer-facing-ai-application-tutorial.md | V2 cram: FDE/FDE_System_Design_Interview_20_Scenarios/Version_2/chapter-15-observability-customer-facing-ai-application-tutorial_v2.md | Site: site/content/modules/01-customer-discovery-and-decomposition/system-design/worksheets/observability-customer-facing-ai-application.md | K25: worksheet md + answer key md + V1/V2 tutorials + site page | L25: Yes | M25: Source: The Forward Deployed Engineer System Design Interview (Kindle). Ch 21 V1 also has an uncondensed tutorial. | N25: G14_Observability_And_Production_Diagnosis/ | O25: https://forward-deployed-sigma.vercel.app/modules/15-fde-case-studies/delivery-evaluation-operations/observability-and-production-diagnosis
A26: 25 | B26: Worksheet + answer key | C26: — standalone | D26: Prepare on its own | E26: Configurable platform for customer-specific workflows — config over forks. Related to G15 but a different problem. | F26: Configurable Platform for Customer-Specific Workflows (book ch 17) | G26: FDE System Design Interview — 20 Scenarios (Version 3) | H26: FDE/FDE_System_Design_Interview_20_Scenarios/Version_3/17_configurable_platform_customer_specific_workflows.md | I26: FDE/FDE_System_Design_Interview_20_Scenarios/Version_3/answer_keys/17_configurable_platform_customer_specific_workflows_answer_key.md | J26: V1 long tutorial: FDE/FDE_System_Design_Interview_20_Scenarios/Version_1/chapter-17-configurable-platform-customer-specific-workflows-tutorial.md | V2 cram: FDE/FDE_System_Design_Interview_20_Scenarios/Version_2/chapter-17-configurable-platform-customer-specific-workflows-tutorial_v2.md | Site: site/content/modules/01-customer-discovery-and-decomposition/system-design/worksheets/configurable-platform-customer-specific-workflows.md | K26: worksheet md + answer key md + V1/V2 tutorials + site page | L26: Yes | M26: Source: The Forward Deployed Engineer System Design Interview (Kindle). Ch 21 V1 also has an uncondensed tutorial. | N26: Standalone/25_Configurable_Platform_Customer_Workflows/ [copied source files (folder)] | O26: https://forward-deployed-sigma.vercel.app/modules/15-fde-case-studies/standalone-designs/configurable-platform-customer-workflows
A27: 26 | B27: Worksheet + answer key | C27: — standalone | D27: Prepare on its own | E27: Enterprise chatbot platform for 40k employees — build vs license, hosting by data class, shadow AI. No sibling. | F27: Enterprise Chatbot Platform (book ch 21) | G27: FDE System Design Interview — 20 Scenarios (Version 3) | H27: FDE/FDE_System_Design_Interview_20_Scenarios/Version_3/21_enterprise_chatbot_platform.md | I27: FDE/FDE_System_Design_Interview_20_Scenarios/Version_3/answer_keys/21_enterprise_chatbot_platform_answer_key.md | J27: V1 long tutorial: FDE/FDE_System_Design_Interview_20_Scenarios/Version_1/chapter-21-enterprise-chatbot-platform-tutorial-condensed.md | V2 cram: FDE/FDE_System_Design_Interview_20_Scenarios/Version_2/chapter-21-enterprise-chatbot-platform-tutorial-condensed_v2.md | Site: site/content/modules/01-customer-discovery-and-decomposition/system-design/worksheets/enterprise-chatbot-platform.md | K27: worksheet md + answer key md + V1/V2 tutorials + site page | L27: Yes | M27: Source: The Forward Deployed Engineer System Design Interview (Kindle). Ch 21 V1 also has an uncondensed tutorial. | N27: Standalone/26_Enterprise_Chatbot_Platform/ [copied source files (folder)] | O27: https://forward-deployed-sigma.vercel.app/modules/15-fde-case-studies/standalone-designs/enterprise-chatbot-platform
... A37: 36 | B37: Worksheet + answer key | C37: G06 Natural language over governed data (NL-to-SQL, KPI copilot) | D37: Covered by anchor — read delta only | E37: Executive persona of the same system. Delta: variance explanation + escalate to analysts. 5 minutes. | F37: Executive Dashboard Copilot | G37: Complete GEN AI FDE Interview System — Module 01 worksheets | H37: FDE/Complete GEN AI FDE Interview System — Core + GenAI/01_CUSTOMER_DISCOVERY_AND_DECOMPOSITION/04_CASE_STUDY_WORKSHEET/10_executive_dashboard_copilot.md | I37: FDE/Complete GEN AI FDE Interview System — Core + GenAI/01_CUSTOMER_DISCOVERY_AND_DECOMPOSITION/04_CASE_STUDY_WORKSHEET/answer_keys/answer-keys-in-md/10_executive_dashboard_copilot_answer_key.md | J37: Site: site/content/modules/01-customer-discovery-and-decomposition/core/worksheets/executive-dashboard-copilot.md | K37: worksheet md + answer key md/docx + site page | L37: Yes | M37: Answer keys also as docx (untracked) and in the canonical combined docx. | N37: G06_NL_Over_Governed_Data/ | O37: https://forward-deployed-sigma.vercel.app/modules/15-fde-case-studies/knowledge-retrieval/nl-over-governed-data
A38: 37 | B38: Mock interview | C38: G02 Customer-support automation | D38: Covered by anchor — read delta only | E38: Mock-interview transcript of the same system. Use for a timed run, not new content. | F38: Agentic Support Workflow | G38: Complete GEN AI FDE Interview System — Module 07 mocks | H38: FDE/Complete GEN AI FDE Interview System — Core + GenAI/07_MOCK_INTERVIEWS_AND_SCORECARDS/02_SHORT_PRACTICE_MOCK/02_agentic_support_workflow_mock.md | I38: FDE/Complete GEN AI FDE Interview System — Core + GenAI/07_MOCK_INTERVIEWS_AND_SCORECARDS/03_FULL_MOCK_INTERVIEWS/02_agentic_support_workflow_full_mock.md | K38: short mock md + full mock md | L38: Yes | M38: Only mock not drawn from a Module 01 worksheet. The other 4 mocks are listed against their worksheet rows. | N38: G02_Customer_Support_Automation/ | O38: https://forward-deployed-sigma.vercel.app/modules/15-fde-case-studies/agents-that-act/customer-support-automation
A39: 38 | B39: Cost/latency drill case | C39: G01 Enterprise knowledge assistant (permission-aware RAG) | D39: Same system, cost/latency question — 10-min add-on | E39: Attach to #15 Enterprise Knowledge Assistant (G01). Driver: Input tokens: whole corpus stuffed into long context, plus unconditional rerank. Lever: Calibrated top-k with metadata filters; rerank only ambiguous queries; route simple clause lookups to a mid-tier model. Prove: Cost per request; Recall@k; citation correctness; retrieval vs model latency split. Line: Legal quality forces citations and escalation, budget forces top-k and routing, the 8-second target rules out heavy rerank on every query. Pilot on a limited document set with cost instrumented from day one. (Drill Add-ons tab) | F39: Enterprise legal RAG assistant under strict cost limits | G39: Study Guides — Cost & Latency Optimization (§16) | H39: Study_Guides/Cost_Latency_Optimization/CRAM_SHEET_S15_S16.md | J39: Study_Guides/Cost_Latency_Optimization/Cost_Latency_Drills_S15_S16.html (drill deck) | K39: md section + html drill deck | L39: Yes | M39: §16 Case 1. Format: prompt / ask / weak vs strong answer / architecture / trade-offs / metrics / recommendation. | N39: G01_Enterprise_Knowledge_Assistant/ | O39: https://forward-deployed-sigma.vercel.app/modules/15-fde-case-studies/knowledge-retrieval/enterprise-knowledge-assistant
A40: 39 | B40: Cost/latency drill case | C40: G02 Customer-support automation | D40: Same system, cost/latency question — 10-min add-on | E40: Attach to #18 AI Customer-Support Automation (G02). Driver: Model spend on repeated FAQ traffic that needs no LLM. Lever: Intent router in front; permission-aware semantic cache for safe FAQs; small model for classification; tools only for account data. Prove: Cost per resolved ticket; deflection rate; cache hit rate; P95 latency. Line: Reduce cost by workflow, not across the board. Cache the FAQ path, route by intent, protect the account-data path. (Drill Add-ons tab) | F40: Support chatbot with 10,000 daily users | G40: Study Guides — Cost & Latency Optimization (§16) | H40: Study_Guides/Cost_Latency_Optimization/CRAM_SHEET_S15_S16.md | J40: Study_Guides/Cost_Latency_Optimization/Cost_Latency_Drills_S15_S16.html (drill deck) | K40: md section + html drill deck | L40: Yes | M40: §16 Case 2. Format: prompt / ask / weak vs strong answer / architecture / trade-offs / metrics / recommendation. | N40: G02_Customer_Support_Automation/ | O40: https://forward-deployed-sigma.vercel.app/modules/15-fde-case-studies/agents-that-act/customer-support-automation
A41: 40 | B41: Cost/latency drill case | C41: G05 Sales copilot / account research | D41: Same system, cost/latency question — 10-min add-on | E41: Attach to #28 Sales Copilot (G05). Driver: Agent steps and serial tool calls. Lever: Trace first; cap steps; parallelise read-only calls; precompute account snapshots; deterministic route for common requests. Prove: Agent step count; tool latency; cache hit rate; timeout rate. Line: Replace the open-ended agent loop with a bounded execution graph. Common CRM operations are deterministic and cache-backed; the agent handles only the ambiguous next step. (Drill Add-ons tab) | F41: Reduce latency for an agentic CRM assistant | G41: Study Guides — Cost & Latency Optimization (§16) | H41: Study_Guides/Cost_Latency_Optimization/CRAM_SHEET_S15_S16.md | J41: Study_Guides/Cost_Latency_Optimization/Cost_Latency_Drills_S15_S16.html (drill deck) | K41: md section + html drill deck | L41: Yes | M41: §16 Case 3. Format: prompt / ask / weak vs strong answer / architecture / trade-offs / metrics / recommendation. | N41: G05_Sales_Copilot/ | O41: https://forward-deployed-sigma.vercel.app/modules/15-fde-case-studies/agents-that-act/sales-copilot
A42: 41 | B42: Cost/latency drill case | C42: G07 Secure multi-tenant AI platform | D42: Same system, cost/latency question — 10-min add-on | E42: Attach to #16 Secure Multi-Tenant AI Platform (G07). Driver: Uncontrolled spend with no attribution, and a shared cache that leaks across tenants. Lever: Tenant-aware gateway with budget check before the model call; cache keyed on tenant + permission signature; quota alerts. Prove: Cost per tenant; quota usage; cross-tenant access tests; cache hit rate by tenant. Line: Make tenant_id and permission_signature first-class in every service. Budgets are contractual, so meter before the call, not after. (Drill Add-ons tab) | F42: Multi-tenant GenAI platform with per-customer budgets | G42: Study Guides — Cost & Latency Optimization (§16) | H42: Study_Guides/Cost_Latency_Optimization/CRAM_SHEET_S15_S16.md | J42: Study_Guides/Cost_Latency_Optimization/Cost_Latency_Drills_S15_S16.html (drill deck) | K42: md section + html drill deck | L42: Yes | M42: §16 Case 4. Format: prompt / ask / weak vs strong answer / architecture / trade-offs / metrics / recommendation. | N42: G07_Secure_Multi_Tenant_AI_Platform/ | O42: https://forward-deployed-sigma.vercel.app/modules/15-fde-case-studies/platforms-and-scale/secure-multi-tenant-ai-platform
A43: 42 | B43: Cost/latency drill case | C43: G10 High-volume batch / document pipeline | D43: Same system, cost/latency question — 10-min add-on | E43: Attach to #21 High-Volume Batch Inference (G10). Driver: Reprocessing unchanged documents on a premium model. Lever: Content hash and change detection; dedupe; cheaper model in batch mode; sampled strong-model audit. Prove: Changed ratio; cost per document; queue depth; eval score on the sample. Line: Never reprocess an unchanged document without a reason. Batch buys throughput not latency, so quality is proven by sampling. (Drill Add-ons tab) | F43: Document summarization pipeline for batch processing | G43: Study Guides — Cost & Latency Optimization (§16) | H43: Study_Guides/Cost_Latency_Optimization/CRAM_SHEET_S15_S16.md | J43: Study_Guides/Cost_Latency_Optimization/Cost_Latency_Drills_S15_S16.html (drill deck) | K43: md section + html drill deck | L43: Yes | M43: §16 Case 5. Format: prompt / ask / weak vs strong answer / architecture / trade-offs / metrics / recommendation. | N43: G10_High_Volume_Batch_Pipeline/ | O43: https://forward-deployed-sigma.vercel.app/modules/15-fde-case-studies/platforms-and-scale/high-volume-batch-pipeline
A44: 43 | B44: Cost/latency drill case | C44: G16 Real-time call assistant | D44: Same system, cost/latency question — 10-min add-on | E44: Attach to #59 Call Assistant (G16). Driver: Synchronous live CRM lookup plus a large model inside the 3-second window. Lever: Precompute account context before the call; small prompt with a fast model streamed during; enrichment and CRM update async after. Prove: First-token latency; total latency; precompute hit rate; user accept rate; timeout rate. Line: Sub-3 seconds is a workflow design problem, not a model choice. Split before, during and after the call. (Drill Add-ons tab) | F44: Real-time sales assistant, sub-3-second response | G44: Study Guides — Cost & Latency Optimization (§16) | H44: Study_Guides/Cost_Latency_Optimization/CRAM_SHEET_S15_S16.md | J44: Study_Guides/Cost_Latency_Optimization/Cost_Latency_Drills_S15_S16.html (drill deck) | K44: md section + html drill deck | L44: Yes | M44: §16 Case 6. Format: prompt / ask / weak vs strong answer / architecture / trade-offs / metrics / recommendation. | N44: G16_Real_Time_Call_Assistant/ | O44: https://forward-deployed-sigma.vercel.app/modules/15-fde-case-studies/agents-that-act/real-time-call-assistant
A45: 44 | B45: Cost/latency drill case | C45: G14 Observability and production diagnosis | D45: Same system, cost/latency question — 10-min add-on | E45: Attach to #24 Observability for a Customer-Facing AI App (G14). Driver: Unknown until attributed: usually retries, agent loops, batch or eval jobs, or an integration loop. Lever: Spend circuit breaker first; attribute by tenant and feature; cap output; pause batch and eval; downgrade premium routing; tenant quotas; then root cause. Prove: Cost per minute; tokens per request; model distribution; retry count; agent steps; tenant usage. Line: Contain, attribute, then diagnose. Keep low-cost safe paths online while disabling runaway paths. The real lesson is that budget guardrails must exist before launch. (Drill Add-ons tab) | F45: Incident: LLM costs exploded after launch | G45: Study Guides — Cost & Latency Optimization (§16) | H45: Study_Guides/Cost_Latency_Optimization/CRAM_SHEET_S15_S16.md | J45: Study_Guides/Cost_Latency_Optimization/Cost_Latency_Drills_S15_S16.html (drill deck) | K45: md section + html drill deck | L45: Yes | M45: §16 Case 7. Format: prompt / ask / weak vs strong answer / architecture / trade-offs / metrics / recommendation. | N45: G14_Observability_And_Production_Diagnosis/ | O45: https://forward-deployed-sigma.vercel.app/modules/15-fde-case-studies/delivery-evaluation-operations/observability-and-production-diagnosis
A46: 45 | B46: Decomposition prompt | C46: G01 Enterprise knowledge assistant (permission-aware RAG) | D46: Covered by anchor — read delta only | E46: Question-bank version of the same prompt. Talking points only. | F46: Enterprise Knowledge Assistant | G46: OpenAI Applied — Problem Decomposition question bank | H46: OpenAI_Applied/Sample_Questions/OpenAI Applied_Engineer_Problem_Decomposition_Questions.md | J46: Same folder: .html render of this markdown (openai_decomposition_interview_prep.html is a DIFFERENT list, rows 66-84) | K46: md + html | L46: Yes | M46: Question 1. Talking points + likely follow-up, not a full worked design. | N46: G01_Enterprise_Knowledge_Assistant/ | O46: https://forward-deployed-sigma.vercel.app/modules/15-fde-case-studies/knowledge-retrieval/enterprise-knowledge-assistant
A47: 46 | B47: Decomposition prompt | C47: G02 Customer-support automation | D47: Covered by anchor — read delta only | E47: Question-bank version. Talking points only. | F47: Customer-Support Agent | G47: OpenAI Applied — Problem Decomposition question bank | H47: OpenAI_Applied/Sample_Questions/OpenAI Applied_Engineer_Problem_Decomposition_Questions.md | J47: Same folder: .html render of this markdown (openai_decomposition_interview_prep.html is a DIFFERENT list, rows 66-84) | K47: md + html | L47: Yes | M47: Question 2. Talking points + likely follow-up, not a full worked design. | N47: G02_Customer_Support_Automation/ | O47: https://forward-deployed-sigma.vercel.app/modules/15-fde-case-studies/agents-that-act/customer-support-automation
A48: 47 | B48: Decomposition prompt | C48: G08 Document review / extraction copilot with policy check | D48: Covered by anchor — read delta only | E48: Question-bank claims-processing version. Talking points only. | F48: Claims-Processing Assistant | G48: OpenAI Applied — Problem Decomposition question bank | H48: OpenAI_Applied/Sample_Questions/OpenAI Applied_Engineer_Problem_Decomposition_Questions.md | J48: Same folder: .html render of this markdown (openai_decomposition_interview_prep.html is a DIFFERENT list, rows 66-84) | K48: md + html | L48: Yes | M48: Question 3. Talking points + likely follow-up, not a full worked design. | N48: G08_Document_Review_Copilot/ | O48: https://forward-deployed-sigma.vercel.app/modules/15-fde-case-studies/knowledge-retrieval/document-review-copilot
A49: 48 | B49: Decomposition prompt | C49: G05 Sales copilot / account research | D49: Covered by anchor — read delta only | E49: Question-bank version. Talking points only. | F49: AI-Powered Sales or Account-Research Assistant | G49: OpenAI Applied — Problem Decomposition question bank | H49: OpenAI_Applied/Sample_Questions/OpenAI Applied_Engineer_Problem_Decomposition_Questions.md | J49: Same folder: .html render of this markdown (openai_decomposition_interview_prep.html is a DIFFERENT list, rows 66-84) | K49: md + html | L49: Yes | M49: Question 4. Talking points + likely follow-up, not a full worked design. | N49: G05_Sales_Copilot/ | O49: https://forward-deployed-sigma.vercel.app/modules/15-fde-case-studies/agents-that-act/sales-copilot
A50: 49 | B50: Decomposition prompt | C50: G10 High-volume batch / document pipeline | D50: Covered by anchor — read delta only | E50: Extraction-platform framing (bank, millions of documents). Delta: extraction schema + QA sampling. | F50: Enterprise Document-Processing Platform | G50: OpenAI Applied — Problem Decomposition question bank | H50: OpenAI_Applied/Sample_Questions/OpenAI Applied_Engineer_Problem_Decomposition_Questions.md | J50: Same folder: .html render of this markdown (openai_decomposition_interview_prep.html is a DIFFERENT list, rows 66-84) | K50: md + html | L50: Yes | M50: Question 5. Talking points + likely follow-up, not a full worked design. | N50: G10_High_Volume_Batch_Pipeline/ | O50: https://forward-deployed-sigma.vercel.app/modules/15-fde-case-studies/platforms-and-scale/high-volume-batch-pipeline
... A64: 63 | B64: Running module case | C64: G01 Enterprise knowledge assistant (permission-aware RAG) | D64: Covered by anchor — read delta only | E64: Running case (Meridian Assist) the anchor is built on; also your STAR story. Read once for narrative, not design. | F64: Meridian Assist — enterprise RAG (fictional insurer) | G64: Handbook Module 04 — Enterprise RAG | H64: Handbook/04_Enterprise_RAG/01_Why_Enterprise_Changes_The_Problem.md | J64: FDE/Star_Stories/Meridian_Assist_Enterprise_RAG/ (deep-dive + conversational guide) | Handbook/11_Telling_The_Story/stories/ (copy) | Whiteboard script 01 | K64: md | L64: Yes | M64: One company threaded through the whole module; also told as a STAR story. | N64: G01_Enterprise_Knowledge_Assistant/ | O64: https://forward-deployed-sigma.vercel.app/modules/15-fde-case-studies/knowledge-retrieval/enterprise-knowledge-assistant
A65: 64 | B65: Running module case | C65: G15 Agent platform for non-technical users | D65: Covered by anchor — read delta only | E65: Module 05 running case (Cascade Robotics) + code project. Same design in prose. | F65: Cascade Robotics — agentic workflow platform | G65: Handbook Module 05 — Agentic Workflow Platforms | H65: Handbook/05_Agentic_Workflow_Platforms/01_The_Problem_In_Plain_English.md | J65: Handbook/05_Agentic_Workflow_Platforms/project/data/case_study.json (runnable fixture) | Whiteboard script 03 | K65: md + json fixture + code project | L65: Yes | N65: G15_Agent_Platform_For_Non_Technical_Users/ | O65: https://forward-deployed-sigma.vercel.app/modules/15-fde-case-studies/platforms-and-scale/agent-platform-for-non-technical-users
A66: 65 | B66: Running module case | C66: G12 Delivery framework: scoping doc to deployed agent in two weeks | D66: Covered by anchor — read delta only | E66: Module 10 running case + the AI_Engineer interview script and code project. Same content in prose form. | F66: Northwind Logistics — Tier-1 support triage agent, scoping to production in two weeks | G66: Handbook Module 10 — FDE Delivery Operating Model | H66: Handbook/10_FDE_Delivery_Operating_Model/03_Scoping_To_Production_In_Two_Weeks.md | J66: Handbook/10_FDE_Delivery_Operating_Model/project/data/case_study.json | AI_Engineer/Delivery Framework from Scoping to Delivery/INTERVIEW_SCRIPT.md (+ data/case_study.json) | Whiteboard script 04 | K66: md + json fixture + code project | L66: Yes | N66: G12_Scoping_To_Deployed_Agent/ | O66: https://forward-deployed-sigma.vercel.app/modules/15-fde-case-studies/delivery-evaluation-operations/scoping-to-deployed-agent
A67: 66 | B67: Reported prompt | C67: G17 Logistics exception handling / shipment rerouting agent | D67: Covered by anchor — read delta only | E67: Reported OpenAI FDE prompt: rerouting over SAP + weather + 500 warehouse managers. Delta: name the evaluation plan unprompted and the stakeholder surface (regional systems). | F67: Logistics shipment-rerouting agent (SAP data, weather APIs, 500 warehouse managers): build it and evaluate it | G67: OpenAI Applied — 19 reported prompts (decomposition interview prep HTML, Tier 1) | H67: OpenAI_Applied/Sample_Questions/openai_decomposition_interview_prep.html | J67: Framework for all 19: section 4 of the same HTML ('The Framework That Wins the Round'); Tier 2 probes in section 3 | K67: html | L67: Yes | M67: Tier 1 prompt 1 · reported at OpenAI FDE · tests: multi-system data unification, stakeholder surface area, evaluation as first-class. Pattern: business goal first, data second, model last. | N67: G17_Logistics_Exception_Handling/ | O67: https://forward-deployed-sigma.vercel.app/modules/15-fde-case-studies/agents-that-act/logistics-exception-handling
A68: 67 | B68: Reported prompt | C68: — standalone | D68: Prepare on its own | E68: 911 response times — decomposition classic. Shares the method (mission → inputs → sequencing by risk) with #68/#69, not the case. Prepare the framework once, the domain separately. | F68: City 911 emergency response times (call data, traffic sensors, ambulance GPS): 60 minutes, go | G68: OpenAI Applied — 19 reported prompts (decomposition interview prep HTML, Tier 1) | H68: OpenAI_Applied/Sample_Questions/openai_decomposition_interview_prep.html | J68: Framework for all 19: section 4 of the same HTML ('The Framework That Wins the Round'); Tier 2 probes in section 3 | K68: html | L68: Yes | M68: Tier 1 prompt 2 · reported at Decomposition classic · tests: mission clarification (response time vs cost vs equity), input mapping, sequencing by risk. Pattern: business goal first, data second, model last. | N68: Standalone/Decomposition_Classics_67_68_69/Decomposition_Classics_67_68_69.md | O68: https://forward-deployed-sigma.vercel.app/modules/15-fde-case-studies/judgement-and-decomposition/decomposition-classics-67-68-69
A69: 68 | B69: Reported prompt | C69: — standalone | D69: Prepare on its own | E69: Bank fraud unification after M&A — decomposition classic; 90-day scoping with poor labels. Method shared with #67/#69; overlaps #62 poor data. | F69: Regional bank: unify fraud detection across three M&A legacy systems, inconsistent labels: scope the first 90 days | G69: OpenAI Applied — 19 reported prompts (decomposition interview prep HTML, Tier 1) | H69: OpenAI_Applied/Sample_Questions/openai_decomposition_interview_prep.html | J69: Framework for all 19: section 4 of the same HTML ('The Framework That Wins the Round'); Tier 2 probes in section 3 | K69: html | L69: Yes | M69: Tier 1 prompt 3 · reported at Decomposition classic · tests: data-quality realism, phased scoping, regulatory constraints. Pattern: business goal first, data second, model last. | N69: Standalone/Decomposition_Classics_67_68_69/Decomposition_Classics_67_68_69.md | O69: https://forward-deployed-sigma.vercel.app/modules/15-fde-case-studies/judgement-and-decomposition/decomposition-classics-67-68-69
A70: 69 | B70: Reported prompt | C70: — standalone | D70: Prepare on its own | E70: Hospital medication errors — decomposition classic; HITL and safety-first. Method shared with #67/#68. | F70: Hospital network: reduce post-surgery medication errors (records, dispensing logs, nurse schedules): where do you start | G70: OpenAI Applied — 19 reported prompts (decomposition interview prep HTML, Tier 1) | H70: OpenAI_Applied/Sample_Questions/openai_decomposition_interview_prep.html | J70: Framework for all 19: section 4 of the same HTML ('The Framework That Wins the Round'); Tier 2 probes in section 3 | K70: html | L70: Yes | M70: Tier 1 prompt 4 · reported at Decomposition classic · tests: high-stakes HITL design, safety-first decomposition. Pattern: business goal first, data second, model last. | N70: Standalone/Decomposition_Classics_67_68_69/Decomposition_Classics_67_68_69.md | O70: https://forward-deployed-sigma.vercel.app/modules/15-fde-case-studies/judgement-and-decomposition/decomposition-classics-67-68-69
A71: 70 | B71: Reported prompt | C71: G01 Enterprise knowledge assistant (permission-aware RAG) | D71: Same system, cost/latency question — 10-min add-on | E71: Latency angle: 1.5 s naive RAG to sub-100 ms. Decompose the budget: cache embeddings and retrieval, pre-filter, skip rerank on cache hits, small model, stream. Say what 100 ms rules out (any LLM generation on the hot path). | F71: Sub-100 ms LLM-powered search when the naive RAG flow is 1.5 s: walk me to 100 ms | G71: OpenAI Applied — 19 reported prompts (decomposition interview prep HTML, Tier 1) | H71: OpenAI_Applied/Sample_Questions/openai_decomposition_interview_prep.html | J71: Framework for all 19: section 4 of the same HTML ('The Framework That Wins the Round'); Tier 2 probes in section 3 | K71: html | L71: Yes | M71: Tier 1 prompt 5 · reported at OpenAI perf · tests: latency budget decomposition across retrieval, generation and network. Pattern: business goal first, data second, model last. | N71: G01_Enterprise_Knowledge_Assistant/ | O71: https://forward-deployed-sigma.vercel.app/modules/15-fde-case-studies/knowledge-retrieval/enterprise-knowledge-assistant
A72: 71 | B72: Reported prompt | C72: G18 Consumer-scale chat service | D72: ANCHOR — prepare this | E72: Anchor by default: no worked design in the repo. Build the outline from the HTML's framework section plus G14 observability and the cost drivers. | F72: Design ChatGPT | G72: OpenAI Applied — 19 reported prompts (decomposition interview prep HTML, Tier 1) | H72: OpenAI_Applied/Sample_Questions/openai_decomposition_interview_prep.html | J72: Framework for all 19: section 4 of the same HTML ('The Framework That Wins the Round'); Tier 2 probes in section 3 | K72: html | L72: Yes | M72: Tier 1 prompt 6 · reported at OpenAI · tests: consumer-scale chat service design. Pattern: business goal first, data second, model last. | N72: G18_Consumer_Scale_Chat_Service/ | O72: https://forward-deployed-sigma.vercel.app/modules/15-fde-case-studies/platforms-and-scale/consumer-scale-chat-service
A73: 72 | B73: Reported prompt | C73: G01 Enterprise knowledge assistant (permission-aware RAG) | D73: Covered by anchor — read delta only | E73: Reported OpenAI prompt: 'LLM-powered enterprise search'. The anchor is the answer. | F73: Design an AI chatbot / an LLM-powered enterprise search system | G73: OpenAI Applied — 19 reported prompts (decomposition interview prep HTML, Tier 1) | H73: OpenAI_Applied/Sample_Questions/openai_decomposition_interview_prep.html | J73: Framework for all 19: section 4 of the same HTML ('The Framework That Wins the Round'); Tier 2 probes in section 3 | K73: html | L73: Yes | M73: Tier 1 prompt 7 · reported at OpenAI · tests: enterprise search design. Pattern: business goal first, data second, model last. | N73: G01_Enterprise_Knowledge_Assistant/ | O73: https://forward-deployed-sigma.vercel.app/modules/15-fde-case-studies/knowledge-retrieval/enterprise-knowledge-assistant
A74: 73 | B74: Reported prompt | C74: G19 Model development and post-training | D74: Covered by anchor — read delta only | E74: Delta: training infrastructure under compute/data constraints (distributed training, data pipeline, checkpointing). | F74: Design a scalable, efficient system for training an LLM given compute and data constraints | G74: OpenAI Applied — 19 reported prompts (decomposition interview prep HTML, Tier 1) | H74: OpenAI_Applied/Sample_Questions/openai_decomposition_interview_prep.html | J74: Framework for all 19: section 4 of the same HTML ('The Framework That Wins the Round'); Tier 2 probes in section 3 | K74: html | L74: Yes | M74: Tier 1 prompt 8 · reported at OpenAI · tests: training infrastructure under constraints. Pattern: business goal first, data second, model last. | N74: G19_Model_Development_And_Post_Training/ | O74: https://forward-deployed-sigma.vercel.app/modules/15-fde-case-studies/model-development/model-development-and-post-training
A75: 74 | B75: Reported prompt | C75: G20 LLM inference serving infrastructure | D75: Covered by anchor — read delta only | E75: Delta: latency diagnosis walk (tokenization → network → batch → KV cache → post-processing). Also listed under G14. | F75: Diagnose high latency in an LLM inference pipeline (tokenization → network → batch size → KV cache → post-processing) | G75: OpenAI Applied — 19 reported prompts (decomposition interview prep HTML, Tier 1) | H75: OpenAI_Applied/Sample_Questions/openai_decomposition_interview_prep.html | J75: Framework for all 19: section 4 of the same HTML ('The Framework That Wins the Round'); Tier 2 probes in section 3 | K75: html | L75: Yes | M75: Tier 1 prompt 9 · reported at OpenAI favorite · tests: full-stack inference latency reasoning. Pattern: business goal first, data second, model last. | N75: G20_LLM_Inference_Serving/ | O75: https://forward-deployed-sigma.vercel.app/modules/15-fde-case-studies/platforms-and-scale/llm-inference-serving
A76: 75 | B76: Reported prompt | C76: G20 LLM inference serving infrastructure | D76: Covered by anchor — read delta only | E76: Delta: single-GPU, 100-per-batch, synchronous waiting. The anchor's intake/batching section covers it. | F76: Inference batching system: one GPU, up to 100 inputs per batch, synchronous users: intake, batching, GPU processing, response routing | G76: OpenAI Applied — 19 reported prompts (decomposition interview prep HTML, Tier 1) | H76: OpenAI_Applied/Sample_Questions/openai_decomposition_interview_prep.html | J76: Framework for all 19: section 4 of the same HTML ('The Framework That Wins the Round'); Tier 2 probes in section 3 | K76: html | L76: Yes | M76: Tier 1 prompt 10 · reported at Anthropic · tests: batching, queuing, synchronous waiting. Pattern: business goal first, data second, model last. | N76: G20_LLM_Inference_Serving/ | O76: https://forward-deployed-sigma.vercel.app/modules/15-fde-case-studies/platforms-and-scale/llm-inference-serving
A77: 76 | B77: Reported prompt | C77: G20 LLM inference serving infrastructure | D77: ANCHOR — prepare this | E77: Anchor by default: the end-to-end batching prompt with its follow-ups (which GPU has capacity, failover) is the superset. No worked design in the repo. | F77: End-to-end LLM batching system: intake, batching, GPU routing and load balancing, delivery. Follow-ups: which GPU has capacity, failover | G77: OpenAI Applied — 19 reported prompts (decomposition interview prep HTML, Tier 1) | H77: OpenAI_Applied/Sample_Questions/openai_decomposition_interview_prep.html | J77: Framework for all 19: section 4 of the same HTML ('The Framework That Wins the Round'); Tier 2 probes in section 3 | K77: html | L77: Yes | M77: Tier 1 prompt 11 · reported at Anthropic · tests: distributed-systems fundamentals: capacity discovery, failover. Pattern: business goal first, data second, model last. | N77: G20_LLM_Inference_Serving/ | O77: https://forward-deployed-sigma.vercel.app/modules/15-fde-case-studies/platforms-and-scale/llm-inference-serving
A78: 77 | B78: Reported prompt | C78: G20 LLM inference serving infrastructure | D78: Covered by anchor — read delta only | E78: Delta: 100k requests per second. Add load balancing, backpressure, admission control. | F78: Token-generation service handling up to 100,000 requests per second | G78: OpenAI Applied — 19 reported prompts (decomposition interview prep HTML, Tier 1) | H78: OpenAI_Applied/Sample_Questions/openai_decomposition_interview_prep.html | J78: Framework for all 19: section 4 of the same HTML ('The Framework That Wins the Round'); Tier 2 probes in section 3 | K78: html | L78: Yes | M78: Tier 1 prompt 12 · reported at Anthropic · tests: throughput, load balancing, backpressure. Pattern: business goal first, data second, model last. | N78: G20_LLM_Inference_Serving/ | O78: https://forward-deployed-sigma.vercel.app/modules/15-fde-case-studies/platforms-and-scale/llm-inference-serving
... A119: 118 | B119: Cost/latency production scenario | C119: G03 Tool-using agent acting across enterprise systems | D119: Same system, cost/latency question — 10-min add-on | E119: §15 scenario 15: tool-calling workflow times out. Per-tool timeouts, parallel read-only calls, bounded execution graph. | F119: Tool-calling workflow times out | G119: Study Guides — Cost & Latency Optimization (§15, 15 production scenarios) | H119: Study_Guides/Cost_Latency_Optimization/CRAM_SHEET_S15_S16.md | J119: Study_Guides/Cost_Latency_Optimization/Cost_Latency_Drills_S15_S16.html; one-liners in §2 of the cram sheet | K119: md section + html drill deck | L119: Yes | M119: §15 scenario 15. Shape: symptom / ask / causes / metrics / debug / now / later / prevent / say. Same 8 drivers as the drills. | N119: G03_Tool_Using_Agent_With_Safety_Controls/ | O119: https://forward-deployed-sigma.vercel.app/modules/15-fde-case-studies/agents-that-act/tool-using-agent-with-safety-controls
A120: 119 | B120: Cost/latency production scenario | C120: G14 Observability and production diagnosis | D120: Same system, cost/latency question — 10-min add-on | E120: Addition: rate limits at peak. Separate provider 429s from your own gateway limits; jitter, fallback, shed batch traffic. | F120: Rate limits are throttling us at peak | G120: Study Guides — Cost & Latency Optimization (additions beyond the playbook, section E) | H120: Study_Guides/Cost_Latency_Optimization/ADDITIONS_BEYOND_PLAYBOOK.md | K120: md table row | L120: Yes | M120: Section E: a scenario the interviewer may add that §15 does not cover; one 'senior answer' row. | N120: G14_Observability_And_Production_Diagnosis/ | O120: https://forward-deployed-sigma.vercel.app/modules/15-fde-case-studies/delivery-evaluation-operations/observability-and-production-diagnosis
A121: 120 | B121: Cost/latency production scenario | C121: G13 Evaluation and release gating | D121: Same system, cost/latency question — 10-min add-on | E121: Addition: eval bill tripled. LLM-as-judge is inference: stratified sample, cheap judge with strong-judge audit, deltas only. | F121: Costs are fine but the eval bill tripled | G121: Study Guides — Cost & Latency Optimization (additions beyond the playbook, section E) | H121: Study_Guides/Cost_Latency_Optimization/ADDITIONS_BEYOND_PLAYBOOK.md | K121: md table row | L121: Yes | M121: Section E: a scenario the interviewer may add that §15 does not cover; one 'senior answer' row. | N121: G13_Evaluation_And_Release_Gating/ | O121: https://forward-deployed-sigma.vercel.app/modules/15-fde-case-studies/delivery-evaluation-operations/evaluation-and-release-gating
A122: 121 | B122: Cost/latency production scenario | C122: G14 Observability and production diagnosis | D122: Same system, cost/latency question — 10-min add-on | E122: Addition: users abandon mid-stream. Measure against first-token time; cancel the stream and in-flight tool calls on abandon. | F122: Streaming works but users abandon mid-answer | G122: Study Guides — Cost & Latency Optimization (additions beyond the playbook, section E) | H122: Study_Guides/Cost_Latency_Optimization/ADDITIONS_BEYOND_PLAYBOOK.md | K122: md table row | L122: Yes | M122: Section E: a scenario the interviewer may add that §15 does not cover; one 'senior answer' row. | N122: G14_Observability_And_Production_Diagnosis/ | O122: https://forward-deployed-sigma.vercel.app/modules/15-fde-case-studies/delivery-evaluation-operations/observability-and-production-diagnosis

Sheet PDF Casebooks
A1: Casebook | B1: Path (relative to 06_Interview_Prep/) | C1: Tracked in git | D1: Note
A2: GenAI FDE Case Studies | B2: FDE/Complete GEN AI FDE Interview System — Core + GenAI/10_RRK_AND_CASE_STUDY_REFERENCE_LIBRARY/00_GenAI_FDE_Case_Studies.pdf | C2: No | D2: Vendor PDF; individual cases inside not enumerated in this index.
A3: Healthcare Prior-Authorization Assistant (standalone case) | B3: FDE/Complete GEN AI FDE Interview System — Core + GenAI/10_RRK_AND_CASE_STUDY_REFERENCE_LIBRARY/02_Healthcare Prior-Authorization Assistant.pdf | C3: No | D3: Vendor PDF; individual cases inside not enumerated in this index.
A4: GenAI FDE Interview Case Transcripts | B4: FDE/Complete GEN AI FDE Interview System — Core + GenAI/07_MOCK_INTERVIEWS_AND_SCORECARDS/00_GenAI_FDE_Interview_Case_Transcripts.pdf | C4: No | D4: Vendor PDF; individual cases inside not enumerated in this index.
A5: MCP / A2A / LLMOps Case Studies | B5: FDE/Complete GEN AI FDE Interview System — Core + GenAI/09_MCP_A2A_AND_LLMOPS/01_MCP_A2A_LLMOps_Case_Studies.pdf | C5: No | D5: Vendor PDF; individual cases inside not enumerated in this index.
A6: GenAI Evaluation Casebook | B6: FDE/Complete GEN AI FDE Interview System — Core + GenAI/04_EVALUATION_SECURITY_AND_RED_TEAM/01_GenAI Evaluation Casebook.pdf | C6: No | D6: Vendor PDF; individual cases inside not enumerated in this index.
A7: GenAI Red Team and Abuse Case Workbook | B7: FDE/Complete GEN AI FDE Interview System — Core + GenAI/04_EVALUATION_SECURITY_AND_RED_TEAM/00_GenAI_Red_Team_And_Abuse_Case_Workbook.pdf | C7: No | D7: Vendor PDF; individual cases inside not enumerated in this index.
A8: GenAI Incident Simulation Pack | B8: FDE/Complete GEN AI FDE Interview System — Core + GenAI/05_PRODUCTION_DEBUGGING_OBSERVABILITY_AND_OPTIMIZATION/00_GenAI Incident Simulation Pack.pdf | C8: No | D8: Vendor PDF; individual cases inside not enumerated in this index.
A9: Decomposition Practice Workbook | B9: FDE/Complete GEN AI FDE Interview System — Core + GenAI/01_CUSTOMER_DISCOVERY_AND_DECOMPOSITION/01_GenAI_FDE_Decomposition_Practice_Workbook.pdf | C9: No | D9: Vendor PDF; individual cases inside not enumerated in this index.
A10: AI Engineer Interview Kit — RAG/Agents Production Failure Scenarios | B10: Study_Guides/reference/AI_Engineer_Interview_Kit_RAG_Agents_Production_Failure_Scenarios_FINAL.pdf | C10: No | D10: Vendor PDF; individual cases inside not enumerated in this index.
